topsis_manya_102303254/__init__.py
topsis_manya_102303254/cli.py
topsis_manya_102303254/core.py
topsis_manya_102303254-0.1.1.dist-info/licenses/LICENSE
topsis_manya_102303254-0.1.1.dist-info/METADATA
topsis_manya_102303254-0.1.1.dist-info/WHEEL
topsis_manya_102303254-0.1.1.dist-info/entry_points.txt
topsis_manya_102303254-0.1.1.dist-info/top_level.txt
topsis_manya_102303254-0.1.1.dist-info/RECORD
