Metadata-Version: 2.4
Name: Topsis-Manya-102303254
Version: 0.1.1
Summary: TOPSIS command line tool for MCDM problems.
Requires-Python: >=3.8
License-File: LICENSE
Requires-Dist: pandas
Requires-Dist: numpy
Requires-Dist: openpyxl
Dynamic: license-file
